odoo/addons/edi_webservice/README.rst
odoo/addons/edi_webservice/__init__.py
odoo/addons/edi_webservice/__manifest__.py
odoo/addons/edi_webservice/i18n/edi_webservice.pot
odoo/addons/edi_webservice/models/__init__.py
odoo/addons/edi_webservice/models/edi_backend.py
odoo/addons/edi_webservice/readme/CONTRIBUTORS.rst
odoo/addons/edi_webservice/readme/DESCRIPTION.rst
odoo/addons/edi_webservice/security/ir.model.access.csv
odoo/addons/edi_webservice/static/description/icon.png
odoo/addons/edi_webservice/static/description/index.html
odoo/addons/edi_webservice/tests/__init__.py
odoo/addons/edi_webservice/tests/test_edi_webservice.py
odoo/addons/edi_webservice/views/edi_backend.xml
odoo13_addon_edi_webservice-13.0.1.2.2.dist-info/METADATA
odoo13_addon_edi_webservice-13.0.1.2.2.dist-info/WHEEL
odoo13_addon_edi_webservice-13.0.1.2.2.dist-info/top_level.txt
odoo13_addon_edi_webservice-13.0.1.2.2.dist-info/RECORD
