Metadata-Version: 2.1
Name: odoo13-addon-edi-webservice
Version: 13.0.1.2.2
Summary: Defines webservice integration from EDI Exchange records
Home-page: https://github.com/OCA/edi
Author: Creu Blanca,Odoo Community Association (OCA)
Author-email: support@odoo-community.org
License: AGPL-3
Platform: UNKNOWN
Classifier: Programming Language :: Python
Classifier: Framework :: Odoo
Classifier: Framework :: Odoo :: 13.0
Classifier: License :: OSI Approved :: GNU Affero General Public License v3
Classifier: Development Status :: 4 - Beta
Requires-Python: >=3.5
Requires-Dist: odoo13-addon-edi
Requires-Dist: odoo13-addon-webservice
Requires-Dist: odoo (<13.1dev,>=13.0a)
